agentbeats/__init__.py
agentbeats/__main__.py
agentbeats/agent_executor.py
agentbeats/agent_launcher.py
agentbeats/cli.py
agentbeats/logging/__init__.py
agentbeats/logging/context.py
agentbeats/logging/interaction_history.py
agentbeats/logging/logging.py
agentbeats/tests/__init__.py
agentbeats/tests/run_tests.py
agentbeats/tests/test_logging.py
agentbeats/tests/test_sdk_upload.py
agentbeats/tests/test_security.py
agentbeats/tests/test_utils.py
agentbeats/utils/__init__.py
agentbeats/utils/agents/__init__.py
agentbeats/utils/agents/a2a.py
agentbeats/utils/assets/__init__.py
agentbeats/utils/assets/assets.py
agentbeats/utils/commands/__init__.py
agentbeats/utils/commands/ssh.py
agentbeats/utils/deploy/deploy.py
agentbeats/utils/deploy/scenario_manager.py
agentbeats/utils/environment/__init__.py
agentbeats/utils/environment/docker.py
agentbeats/utils/static/__init__.py
agentbeats/utils/static/static.py
backend/__init__.py
backend/a2a_client.py
backend/app.py
backend/auth/middleware.py
backend/auth/supabase.py
backend/db/__init__.py
backend/db/storage.py
backend/mcp/mcp_server.py
backend/routes/__init__.py
backend/routes/agents.py
backend/routes/battles.py
backend/routes/matches.py
backend/routes/websockets.py
backend/services/match_storage.py
backend/services/role_matcher.py
backend/services/scripts/__init__.py
backend/services/scripts/clear_matches.py
backend/services/scripts/populate_matches.py
mcpcp/README.md
mcpcp/__init__.py
agentbeats-1.2.6.dist-info/METADATA
agentbeats-1.2.6.dist-info/WHEEL
agentbeats-1.2.6.dist-info/entry_points.txt
agentbeats-1.2.6.dist-info/top_level.txt
agentbeats-1.2.6.dist-info/RECORD
