Metadata-Version: 2.4
Name: agentbeats
Version: 1.2.6
Summary: AgentBeats SDK for building security-contest AI agents
Author-email: Simon Xie <simonxie2004@outlook.com>
License: MIT
Classifier: Programming Language :: Python :: 3
Classifier: License :: OSI Approved :: MIT License
Requires-Python: >=3.11
Requires-Dist: tomli>=2
Requires-Dist: toml
Requires-Dist: fastmcp
Requires-Dist: fastapi
Requires-Dist: uvicorn
Requires-Dist: pydantic>=2.0.0
Requires-Dist: httpx
Requires-Dist: a2a-sdk>=0.3.0
Requires-Dist: paramiko>=3.5.1
Requires-Dist: openai-agents
Requires-Dist: openai
Requires-Dist: sqlalchemy
Requires-Dist: supabase
Requires-Dist: PyJWT
Requires-Dist: python-dotenv
Requires-Dist: python-multipart
Requires-Dist: google-cloud-storage
